{
  "name": "Monad Full Systems Dev",
  "image": "mcr.microsoft.com/devcontainers/rust:1-bookworm",
  "features": {
    "ghcr.io/devcontainers/features/docker-in-docker:2": {},
    "ghcr.io/devcontainers/features/node:1": {
      "version": "lts"
    },
    "ghcr.io/devcontainers/features/github-cli:1": {}
  },
  "postCreateCommand": "cargo metadata --format-version 1 && bash scripts/drift-check.sh",
  "customizations": {
    "vscode": {
      "extensions": [
        "rust-lang.rust-analyzer",
        "tamasfe.even-better-toml",
        "biomejs.biome",
        "ms-playwright.playwright"
      ]
    }
  }
}
